django_yaml_field/__init__.py
django_yaml_field/fields.py
django_yaml_field-0.1.3.dist-info/licenses/LICENSE
django_yaml_field-0.1.3.dist-info/METADATA
django_yaml_field-0.1.3.dist-info/WHEEL
django_yaml_field-0.1.3.dist-info/top_level.txt
django_yaml_field-0.1.3.dist-info/RECORD
