Metadata-Version: 2.4
Name: django_yaml_field
Version: 0.1.3
Summary: Same as Django JSONField but represent it as YAML (internally stores as JSON)
Home-page: https://github.com/null-none/django-yaml-field
Author: Kalinin Mitko
Author-email: kalinin.mitko@gmail.com
Project-URL: Bug Tracker, https://github.com/null-none/django-yaml-field/issues
Classifier: Programming Language :: Python :: 3
Classifier: License :: OSI Approved :: MIT License
Classifier: Operating System :: OS Independent
Requires-Python: >=3.6
License-File: LICENSE
Requires-Dist: pyyaml
Dynamic: license-file
